keystoneauth_websso/exceptions.py
keystoneauth_websso/loading.py
keystoneauth_websso/plugin.py
keystoneauth_websso-0.2.5.dist-info/LICENSE
keystoneauth_websso-0.2.5.dist-info/METADATA
keystoneauth_websso-0.2.5.dist-info/WHEEL
keystoneauth_websso-0.2.5.dist-info/entry_points.txt
keystoneauth_websso-0.2.5.dist-info/RECORD
