Metadata-Version: 2.3
Name: keystoneauth-websso
Version: 0.2.5
Summary: WebSSO CLI support for OpenStack keystoneauth library
License: Apache-2.0
Author: Ed Timmons
Author-email: ed@delsurf.com
Requires-Python: >=3.8,<4.0
Classifier: Environment :: OpenStack
Classifier: Intended Audience :: Information Technology
Classifier: Intended Audience :: System Administrators
Classifier: License :: OSI Approved :: Apache Software License
Classifier: Operating System :: POSIX :: Linux
Classifier: Programming Language :: Python :: 3
Classifier: Programming Language :: Python :: 3.8
Classifier: Programming Language :: Python :: 3.9
Classifier: Programming Language :: Python :: 3.10
Classifier: Programming Language :: Python :: 3.11
Classifier: Programming Language :: Python :: 3.12
Classifier: Programming Language :: Python :: 3.13
Requires-Dist: keystoneauth1 (>=5.0.0)
Requires-Dist: multipart (>=1.0.0)
Requires-Dist: platformdirs (>=2.5.2)
Project-URL: Repository, https://github.com/vexxhost/keystoneauth-websso
